{
  "id": "294f04f9-ca17-47ab-b043-6bf24150e0f9",
  "prevId": "93da8010-5dbb-4565-84f2-05b9e197012a",
  "version": "7",
  "dialect": "postgresql",
  "tables": {
    "public.assistants": {
      "name": "assistants",
      "schema": "",
      "columns": {
        "assistant_id": {
          "name": "assistant_id",
          "type": "serial",
          "primaryKey": true,
          "notNull": true
        },
        "name": {
          "name": "name",
          "type": "varchar(100)",
          "primaryKey": false,
          "notNull": true
        },
        "gender": {
          "name": "gender",
          "type": "varchar(50)",
          "primaryKey": false,
          "notNull": false
        },
        "avatar_png": {
          "name": "avatar_png",
          "type": "varchar(500)",
          "primaryKey": false,
          "notNull": false
        },
        "personality": {
          "name": "personality",
          "type": "text",
          "primaryKey": false,
          "notNull": false
        }
      },
      "indexes": {},
      "foreignKeys": {},
      "compositePrimaryKeys": {},
      "uniqueConstraints": {},
      "policies": {},
      "checkConstraints": {},
      "isRLSEnabled": false
    },
    "public.dashboards": {
      "name": "dashboards",
      "schema": "",
      "columns": {
        "dashboard_id": {
          "name": "dashboard_id",
          "type": "serial",
          "primaryKey": true,
          "notNull": true
        },
        "theme": {
          "name": "theme",
          "type": "varchar(100)",
          "primaryKey": false,
          "notNull": false
        },
        "custom": {
          "name": "custom",
          "type": "json",
          "primaryKey": false,
          "notNull": false
        },
        "user_id": {
          "name": "user_id",
          "type": "integer",
          "primaryKey": false,
          "notNull": false
        }
      },
      "indexes": {},
      "foreignKeys": {
        "dashboards_user_id_users_user_id_fk": {
          "name": "dashboards_user_id_users_user_id_fk",
          "tableFrom": "dashboards",
          "tableTo": "users",
          "columnsFrom": [
            "user_id"
          ],
          "columnsTo": [
            "user_id"
          ],
          "onDelete": "no action",
          "onUpdate": "no action"
        }
      },
      "compositePrimaryKeys": {},
      "uniqueConstraints": {
        "dashboards_user_id_unique": {
          "name": "dashboards_user_id_unique",
          "nullsNotDistinct": false,
          "columns": [
            "user_id"
          ]
        }
      },
      "policies": {},
      "checkConstraints": {},
      "isRLSEnabled": false
    },
    "public.dialogues": {
      "name": "dialogues",
      "schema": "",
      "columns": {
        "dialogue_id": {
          "name": "dialogue_id",
          "type": "serial",
          "primaryKey": true,
          "notNull": true
        },
        "message": {
          "name": "message",
          "type": "text",
          "primaryKey": false,
          "notNull": true
        },
        "type": {
          "name": "type",
          "type": "varchar(50)",
          "primaryKey": false,
          "notNull": false
        },
        "assistant_id": {
          "name": "assistant_id",
          "type": "integer",
          "primaryKey": false,
          "notNull": false
        }
      },
      "indexes": {},
      "foreignKeys": {
        "dialogues_assistant_id_assistants_assistant_id_fk": {
          "name": "dialogues_assistant_id_assistants_assistant_id_fk",
          "tableFrom": "dialogues",
          "tableTo": "assistants",
          "columnsFrom": [
            "assistant_id"
          ],
          "columnsTo": [
            "assistant_id"
          ],
          "onDelete": "no action",
          "onUpdate": "no action"
        }
      },
      "compositePrimaryKeys": {},
      "uniqueConstraints": {},
      "policies": {},
      "checkConstraints": {},
      "isRLSEnabled": false
    },
    "public.leaderboards": {
      "name": "leaderboards",
      "schema": "",
      "columns": {
        "leaderboard_id": {
          "name": "leaderboard_id",
          "type": "serial",
          "primaryKey": true,
          "notNull": true
        },
        "rank": {
          "name": "rank",
          "type": "integer",
          "primaryKey": false,
          "notNull": false
        },
        "total_points": {
          "name": "total_points",
          "type": "integer",
          "primaryKey": false,
          "notNull": false
        }
      },
      "indexes": {},
      "foreignKeys": {},
      "compositePrimaryKeys": {},
      "uniqueConstraints": {},
      "policies": {},
      "checkConstraints": {},
      "isRLSEnabled": false
    },
    "public.lessons": {
      "name": "lessons",
      "schema": "",
      "columns": {
        "lesson_id": {
          "name": "lesson_id",
          "type": "serial",
          "primaryKey": true,
          "notNull": true
        },
        "title": {
          "name": "title",
          "type": "varchar(255)",
          "primaryKey": false,
          "notNull": true
        },
        "content": {
          "name": "content",
          "type": "text",
          "primaryKey": false,
          "notNull": false
        },
        "difficulty": {
          "name": "difficulty",
          "type": "varchar(50)",
          "primaryKey": false,
          "notNull": false
        },
        "hint": {
          "name": "hint",
          "type": "text",
          "primaryKey": false,
          "notNull": false
        },
        "correct_answer": {
          "name": "correct_answer",
          "type": "text",
          "primaryKey": false,
          "notNull": false
        },
        "assistant_id": {
          "name": "assistant_id",
          "type": "integer",
          "primaryKey": false,
          "notNull": false
        }
      },
      "indexes": {},
      "foreignKeys": {
        "lessons_assistant_id_assistants_assistant_id_fk": {
          "name": "lessons_assistant_id_assistants_assistant_id_fk",
          "tableFrom": "lessons",
          "tableTo": "assistants",
          "columnsFrom": [
            "assistant_id"
          ],
          "columnsTo": [
            "assistant_id"
          ],
          "onDelete": "no action",
          "onUpdate": "no action"
        }
      },
      "compositePrimaryKeys": {},
      "uniqueConstraints": {},
      "policies": {},
      "checkConstraints": {},
      "isRLSEnabled": false
    },
    "public.music": {
      "name": "music",
      "schema": "",
      "columns": {
        "music_id": {
          "name": "music_id",
          "type": "serial",
          "primaryKey": true,
          "notNull": true
        },
        "title": {
          "name": "title",
          "type": "varchar(255)",
          "primaryKey": false,
          "notNull": true
        },
        "artist": {
          "name": "artist",
          "type": "varchar(255)",
          "primaryKey": false,
          "notNull": false
        },
        "duration": {
          "name": "duration",
          "type": "integer",
          "primaryKey": false,
          "notNull": false
        },
        "file_url": {
          "name": "file_url",
          "type": "varchar(500)",
          "primaryKey": false,
          "notNull": false
        },
        "volume": {
          "name": "volume",
          "type": "numeric(3, 2)",
          "primaryKey": false,
          "notNull": false
        }
      },
      "indexes": {},
      "foreignKeys": {},
      "compositePrimaryKeys": {},
      "uniqueConstraints": {},
      "policies": {},
      "checkConstraints": {},
      "isRLSEnabled": false
    },
    "public.password_reset_tokens": {
      "name": "password_reset_tokens",
      "schema": "",
      "columns": {
        "id": {
          "name": "id",
          "type": "serial",
          "primaryKey": true,
          "notNull": true
        },
        "user_id": {
          "name": "user_id",
          "type": "integer",
          "primaryKey": false,
          "notNull": true
        },
        "token": {
          "name": "token",
          "type": "varchar(255)",
          "primaryKey": false,
          "notNull": true
        },
        "expires_at": {
          "name": "expires_at",
          "type": "timestamp",
          "primaryKey": false,
          "notNull": true
        },
        "used_at": {
          "name": "used_at",
          "type": "timestamp",
          "primaryKey": false,
          "notNull": false
        }
      },
      "indexes": {},
      "foreignKeys": {
        "password_reset_tokens_user_id_users_user_id_fk": {
          "name": "password_reset_tokens_user_id_users_user_id_fk",
          "tableFrom": "password_reset_tokens",
          "tableTo": "users",
          "columnsFrom": [
            "user_id"
          ],
          "columnsTo": [
            "user_id"
          ],
          "onDelete": "no action",
          "onUpdate": "no action"
        }
      },
      "compositePrimaryKeys": {},
      "uniqueConstraints": {
        "password_reset_tokens_token_unique": {
          "name": "password_reset_tokens_token_unique",
          "nullsNotDistinct": false,
          "columns": [
            "token"
          ]
        }
      },
      "policies": {},
      "checkConstraints": {},
      "isRLSEnabled": false
    },
    "public.progress": {
      "name": "progress",
      "schema": "",
      "columns": {
        "progress_id": {
          "name": "progress_id",
          "type": "serial",
          "primaryKey": true,
          "notNull": true
        },
        "status": {
          "name": "status",
          "type": "varchar(50)",
          "primaryKey": false,
          "notNull": false
        },
        "score": {
          "name": "score",
          "type": "integer",
          "primaryKey": false,
          "notNull": false
        }
      },
      "indexes": {},
      "foreignKeys": {},
      "compositePrimaryKeys": {},
      "uniqueConstraints": {},
      "policies": {},
      "checkConstraints": {},
      "isRLSEnabled": false
    },
    "public.quizzes": {
      "name": "quizzes",
      "schema": "",
      "columns": {
        "quiz_id": {
          "name": "quiz_id",
          "type": "serial",
          "primaryKey": true,
          "notNull": true
        },
        "topic": {
          "name": "topic",
          "type": "varchar(255)",
          "primaryKey": false,
          "notNull": false
        },
        "difficulty": {
          "name": "difficulty",
          "type": "varchar(50)",
          "primaryKey": false,
          "notNull": false
        },
        "time_limit": {
          "name": "time_limit",
          "type": "integer",
          "primaryKey": false,
          "notNull": false
        }
      },
      "indexes": {},
      "foreignKeys": {},
      "compositePrimaryKeys": {},
      "uniqueConstraints": {},
      "policies": {},
      "checkConstraints": {},
      "isRLSEnabled": false
    },
    "public.study_modes": {
      "name": "study_modes",
      "schema": "",
      "columns": {
        "study_mode_id": {
          "name": "study_mode_id",
          "type": "serial",
          "primaryKey": true,
          "notNull": true
        },
        "background": {
          "name": "background",
          "type": "varchar(255)",
          "primaryKey": false,
          "notNull": false
        },
        "mentor_visibility": {
          "name": "mentor_visibility",
          "type": "boolean",
          "primaryKey": false,
          "notNull": false
        },
        "background_ambience": {
          "name": "background_ambience",
          "type": "varchar(255)",
          "primaryKey": false,
          "notNull": false
        },
        "user_id": {
          "name": "user_id",
          "type": "integer",
          "primaryKey": false,
          "notNull": false
        }
      },
      "indexes": {},
      "foreignKeys": {
        "study_modes_user_id_users_user_id_fk": {
          "name": "study_modes_user_id_users_user_id_fk",
          "tableFrom": "study_modes",
          "tableTo": "users",
          "columnsFrom": [
            "user_id"
          ],
          "columnsTo": [
            "user_id"
          ],
          "onDelete": "no action",
          "onUpdate": "no action"
        }
      },
      "compositePrimaryKeys": {},
      "uniqueConstraints": {
        "study_modes_user_id_unique": {
          "name": "study_modes_user_id_unique",
          "nullsNotDistinct": false,
          "columns": [
            "user_id"
          ]
        }
      },
      "policies": {},
      "checkConstraints": {},
      "isRLSEnabled": false
    },
    "public.user_participates_leaderboard": {
      "name": "user_participates_leaderboard",
      "schema": "",
      "columns": {
        "user_id": {
          "name": "user_id",
          "type": "integer",
          "primaryKey": false,
          "notNull": true
        },
        "leaderboard_id": {
          "name": "leaderboard_id",
          "type": "integer",
          "primaryKey": false,
          "notNull": true
        }
      },
      "indexes": {},
      "foreignKeys": {
        "user_participates_leaderboard_user_id_users_user_id_fk": {
          "name": "user_participates_leaderboard_user_id_users_user_id_fk",
          "tableFrom": "user_participates_leaderboard",
          "tableTo": "users",
          "columnsFrom": [
            "user_id"
          ],
          "columnsTo": [
            "user_id"
          ],
          "onDelete": "no action",
          "onUpdate": "no action"
        },
        "user_participates_leaderboard_leaderboard_id_leaderboards_leaderboard_id_fk": {
          "name": "user_participates_leaderboard_leaderboard_id_leaderboards_leaderboard_id_fk",
          "tableFrom": "user_participates_leaderboard",
          "tableTo": "leaderboards",
          "columnsFrom": [
            "leaderboard_id"
          ],
          "columnsTo": [
            "leaderboard_id"
          ],
          "onDelete": "no action",
          "onUpdate": "no action"
        }
      },
      "compositePrimaryKeys": {
        "user_participates_leaderboard_user_id_leaderboard_id_pk": {
          "name": "user_participates_leaderboard_user_id_leaderboard_id_pk",
          "columns": [
            "user_id",
            "leaderboard_id"
          ]
        }
      },
      "uniqueConstraints": {},
      "policies": {},
      "checkConstraints": {},
      "isRLSEnabled": false
    },
    "public.user_plays_music": {
      "name": "user_plays_music",
      "schema": "",
      "columns": {
        "user_id": {
          "name": "user_id",
          "type": "integer",
          "primaryKey": false,
          "notNull": true
        },
        "music_id": {
          "name": "music_id",
          "type": "integer",
          "primaryKey": false,
          "notNull": true
        }
      },
      "indexes": {},
      "foreignKeys": {
        "user_plays_music_user_id_users_user_id_fk": {
          "name": "user_plays_music_user_id_users_user_id_fk",
          "tableFrom": "user_plays_music",
          "tableTo": "users",
          "columnsFrom": [
            "user_id"
          ],
          "columnsTo": [
            "user_id"
          ],
          "onDelete": "no action",
          "onUpdate": "no action"
        },
        "user_plays_music_music_id_music_music_id_fk": {
          "name": "user_plays_music_music_id_music_music_id_fk",
          "tableFrom": "user_plays_music",
          "tableTo": "music",
          "columnsFrom": [
            "music_id"
          ],
          "columnsTo": [
            "music_id"
          ],
          "onDelete": "no action",
          "onUpdate": "no action"
        }
      },
      "compositePrimaryKeys": {
        "user_plays_music_user_id_music_id_pk": {
          "name": "user_plays_music_user_id_music_id_pk",
          "columns": [
            "user_id",
            "music_id"
          ]
        }
      },
      "uniqueConstraints": {},
      "policies": {},
      "checkConstraints": {},
      "isRLSEnabled": false
    },
    "public.user_takes_quiz": {
      "name": "user_takes_quiz",
      "schema": "",
      "columns": {
        "user_id": {
          "name": "user_id",
          "type": "integer",
          "primaryKey": false,
          "notNull": true
        },
        "quiz_id": {
          "name": "quiz_id",
          "type": "integer",
          "primaryKey": false,
          "notNull": true
        }
      },
      "indexes": {},
      "foreignKeys": {
        "user_takes_quiz_user_id_users_user_id_fk": {
          "name": "user_takes_quiz_user_id_users_user_id_fk",
          "tableFrom": "user_takes_quiz",
          "tableTo": "users",
          "columnsFrom": [
            "user_id"
          ],
          "columnsTo": [
            "user_id"
          ],
          "onDelete": "no action",
          "onUpdate": "no action"
        },
        "user_takes_quiz_quiz_id_quizzes_quiz_id_fk": {
          "name": "user_takes_quiz_quiz_id_quizzes_quiz_id_fk",
          "tableFrom": "user_takes_quiz",
          "tableTo": "quizzes",
          "columnsFrom": [
            "quiz_id"
          ],
          "columnsTo": [
            "quiz_id"
          ],
          "onDelete": "no action",
          "onUpdate": "no action"
        }
      },
      "compositePrimaryKeys": {
        "user_takes_quiz_user_id_quiz_id_pk": {
          "name": "user_takes_quiz_user_id_quiz_id_pk",
          "columns": [
            "user_id",
            "quiz_id"
          ]
        }
      },
      "uniqueConstraints": {},
      "policies": {},
      "checkConstraints": {},
      "isRLSEnabled": false
    },
    "public.user_tracks_progress": {
      "name": "user_tracks_progress",
      "schema": "",
      "columns": {
        "user_id": {
          "name": "user_id",
          "type": "integer",
          "primaryKey": false,
          "notNull": true
        },
        "lesson_id": {
          "name": "lesson_id",
          "type": "integer",
          "primaryKey": false,
          "notNull": true
        },
        "progress_id": {
          "name": "progress_id",
          "type": "integer",
          "primaryKey": false,
          "notNull": true
        }
      },
      "indexes": {},
      "foreignKeys": {
        "user_tracks_progress_user_id_users_user_id_fk": {
          "name": "user_tracks_progress_user_id_users_user_id_fk",
          "tableFrom": "user_tracks_progress",
          "tableTo": "users",
          "columnsFrom": [
            "user_id"
          ],
          "columnsTo": [
            "user_id"
          ],
          "onDelete": "no action",
          "onUpdate": "no action"
        },
        "user_tracks_progress_lesson_id_lessons_lesson_id_fk": {
          "name": "user_tracks_progress_lesson_id_lessons_lesson_id_fk",
          "tableFrom": "user_tracks_progress",
          "tableTo": "lessons",
          "columnsFrom": [
            "lesson_id"
          ],
          "columnsTo": [
            "lesson_id"
          ],
          "onDelete": "no action",
          "onUpdate": "no action"
        },
        "user_tracks_progress_progress_id_progress_progress_id_fk": {
          "name": "user_tracks_progress_progress_id_progress_progress_id_fk",
          "tableFrom": "user_tracks_progress",
          "tableTo": "progress",
          "columnsFrom": [
            "progress_id"
          ],
          "columnsTo": [
            "progress_id"
          ],
          "onDelete": "no action",
          "onUpdate": "no action"
        }
      },
      "compositePrimaryKeys": {
        "user_tracks_progress_user_id_lesson_id_pk": {
          "name": "user_tracks_progress_user_id_lesson_id_pk",
          "columns": [
            "user_id",
            "lesson_id"
          ]
        }
      },
      "uniqueConstraints": {
        "user_tracks_progress_progress_id_unique": {
          "name": "user_tracks_progress_progress_id_unique",
          "nullsNotDistinct": false,
          "columns": [
            "progress_id"
          ]
        }
      },
      "policies": {},
      "checkConstraints": {},
      "isRLSEnabled": false
    },
    "public.users": {
      "name": "users",
      "schema": "",
      "columns": {
        "user_id": {
          "name": "user_id",
          "type": "serial",
          "primaryKey": true,
          "notNull": true
        },
        "username": {
          "name": "username",
          "type": "varchar(100)",
          "primaryKey": false,
          "notNull": true
        },
        "email": {
          "name": "email",
          "type": "varchar(255)",
          "primaryKey": false,
          "notNull": true
        },
        "password": {
          "name": "password",
          "type": "varchar(255)",
          "primaryKey": false,
          "notNull": true
        },
        "assistant_id": {
          "name": "assistant_id",
          "type": "integer",
          "primaryKey": false,
          "notNull": false
        }
      },
      "indexes": {},
      "foreignKeys": {
        "users_assistant_id_assistants_assistant_id_fk": {
          "name": "users_assistant_id_assistants_assistant_id_fk",
          "tableFrom": "users",
          "tableTo": "assistants",
          "columnsFrom": [
            "assistant_id"
          ],
          "columnsTo": [
            "assistant_id"
          ],
          "onDelete": "no action",
          "onUpdate": "no action"
        }
      },
      "compositePrimaryKeys": {},
      "uniqueConstraints": {
        "users_email_unique": {
          "name": "users_email_unique",
          "nullsNotDistinct": false,
          "columns": [
            "email"
          ]
        }
      },
      "policies": {},
      "checkConstraints": {},
      "isRLSEnabled": false
    }
  },
  "enums": {},
  "schemas": {},
  "sequences": {},
  "roles": {},
  "policies": {},
  "views": {},
  "_meta": {
    "columns": {},
    "schemas": {},
    "tables": {}
  }
}